{
  ".": "./esm/index.js",
  "Accordion": "./esm/Accordion/Accordion.js",
  "AccordionActions": "./esm/AccordionActions/AccordionActions.js",
  "AccordionDetails": "./esm/AccordionDetails/AccordionDetails.js",
  "AccordionSummary": "./esm/AccordionSummary/AccordionSummary.js",
  "AppBar": "./esm/AppBar/AppBar.jsAppBar/AppBar.js",
  "Avatar": "./esm/Avatar/Avatar.js",
  "Backdrop": "./esm/Backdrop/Backdrop.js",
  "Badge": "./esm/Badge/Badge.js",
  "BottomNavigation": "./esm/BottomNavigation/BottomNavigation.js",
  "BottomNavigationAction": "./esm/BottomNavigationAction/BottomNavigationAction.js",
  "Box": "./esm/Box/Box.js",
  "Breadcrumbs": "./esm/Breadcrumbs/Breadcrumbs.js",
  "Button": "./esm/Button/Button.js",
  "ButtonBase": "./esm/ButtonBase/ButtonBase.js",
  "ButtonGroup": "./esm/ButtonGroup/ButtonGroup.js",
  "Card": "./esm/Card/Card.js",
  "CardActionArea": "./esm/CardActionArea/CardActionArea.js",
  "CardActions": "./esm/CardActions/CardActions.js",
  "CardContent": "./esm/CardContent/CardContent.js",
  "CardHeader": "./esm/CardHeader/CardHeader.js",
  "CardMedia": "./esm/CardMedia/CardMedia.js",
  "Checkbox": "./esm/Checkbox/Checkbox.js",
  "Chip": "./esm/Chip/Chip.js",
  "CircularProgress": "./esm/CircularProgress/CircularProgress.js",
  "ClickAwayListener": "./esm/ClickAwayListener/ClickAwayListener.js",
  "Collapse": "./esm/Collapse/Collapse.js",
  "Container": "./esm/Container/Container.js",
  "CssBaseline": "./esm/CssBaseline/CssBaseline.js",
  "Dialog": "./esm/Dialog/Dialog.js",
  "DialogActions": "./esm/DialogActions/DialogActions.js",
  "DialogContent": "./esm/DialogContent/DialogContent.js",
  "DialogContentText": "./esm/DialogContentText/DialogContentText.js",
  "DialogTitle": "./esm/DialogTitle/DialogTitle.js",
  "Divider": "./esm/Divider/Divider.jsDivider/Divider.js",
  "Drawer": "./esm/Drawer/Drawer.js",
  "ExpansionPanel": "./esm/ExpansionPanel/ExpansionPanel.js",
  "ExpansionPanelActions": "./esm/ExpansionPanelActions/ExpansionPanelActions.js",
  "ExpansionPanelDetails": "./esm/ExpansionPanelDetails/ExpansionPanelDetails.js",
  "ExpansionPanelSummary": "./esm/ExpansionPanelSummary/ExpansionPanelSummary.js",
  "Fab": "./esm/Fab/Fab.js",
  "Fade": "./esm/Fade/Fade.js",
  "FilledInput": "./esm/FilledInput/FilledInput.js",
  "FormControl": "./esm/FormControl/FormControl.js",
  "FormControlLabel": "./esm/FormControlLabel/FormControlLabel.js",
  "FormGroup": "./esm/FormGroup/FormGroup.js",
  "FormHelperText": "./esm/FormHelperText/FormHelperText.js",
  "FormLabel": "./esm/FormLabel/FormLabel.js",
  "Grid": "./esm/Grid/Grid.js",
  "GridList": "./esm/GridList/GridList.js",
  "GridListTile": "./esm/GridListTile/GridListTile.js",
  "GridListTileBar": "./esm/GridListTileBar/GridListTileBar.js",
  "Grow": "./esm/Grow/Grow.js",
  "Hidden": "./esm/Hidden/Hidden.js",
  "Icon": "./esm/Icon/Icon.js",
  "IconButton": "./esm/IconButton/IconButton.js",
  "Input": "./esm/Input/Input.js",
  "InputAdornment": "./esm/InputAdornment/InputAdornment.js",
  "InputBase": "./esm/InputBase/InputBase.js",
  "InputLabel": "./esm/InputLabel/InputLabel.js",
  "LinearProgress": "./esm/LinearProgress/LinearProgress.js",
  "Link": "./esm/Link/Link.js",
  "List": "./esm/List/List.js",
  "ListItem": "./esm/ListItem/ListItem.jsListItem/ListItem.js",
  "ListItemAvatar": "./esm/ListItemAvatar/ListItemAvatar.js",
  "ListItemIcon": "./esm/ListItemIcon/ListItemIcon.js",
  "ListItemSecondaryAction": "./esm/ListItemSecondaryAction/ListItemSecondaryAction.js",
  "ListItemText": "./esm/ListItemText/ListItemText.js",
  "ListSubheader": "./esm/ListSubheader/ListSubheader.js",
  "Menu": "./esm/Menu/Menu.js",
  "MenuItem": "./esm/MenuItem/MenuItem.js",
  "MenuList": "./esm/MenuList/MenuList.js",
  "MobileStepper": "./esm/MobileStepper/MobileStepper.js",
  "Modal": "./esm/Modal/Modal.js",
  "NativeSelect": "./esm/NativeSelect/NativeSelect.js",
  "NoSsr": "./esm/NoSsr/NoSsr.js",
  "OutlinedInput": "./esm/OutlinedInput/OutlinedInput.js",
  "Paper": "./esm/Paper/Paper.js",
  "Popover": "./esm/Popover/Popover.js",
  "Popper": "./esm/Popper/Popper.js",
  "Portal": "./esm/Portal/Portal.js",
  "Radio": "./esm/Radio/Radio.js",
  "RadioGroup": "./esm/RadioGroup/RadioGroup.js",
  "RootRef": "./esm/RootRef/RootRef.js",
  "ScopedCssBaseline": "./esm/ScopedCssBaseline/ScopedCssBaseline.js",
  "Select": "./esm/Select/Select.js",
  "Slide": "./esm/Slide/Slide.js",
  "Slider": "./esm/Slider/Slider.js",
  "Snackbar": "./esm/Snackbar/Snackbar.js",
  "SnackbarContent": "./esm/SnackbarContent/SnackbarContent.js",
  "Step": "./esm/Step/Step.js",
  "StepButton": "./esm/StepButton/StepButton.js",
  "StepConnector": "./esm/StepConnector/StepConnector.js",
  "StepContent": "./esm/StepContent/StepContent.js",
  "StepIcon": "./esm/StepIcon/StepIcon.js",
  "StepLabel": "./esm/StepLabel/StepLabel.js",
  "Stepper": "./esm/Stepper/Stepper.js",
  "SvgIcon": "./esm/SvgIcon/SvgIcon.js",
  "SwipeableDrawer": "./esm/SwipeableDrawer/SwipeableDrawer.js",
  "Switch": "./esm/Switch/Switch.js",
  "Tab": "./esm/Tab/Tab.js",
  "TabScrollButton": "./esm/TabScrollButton/TabScrollButton.js",
  "Table": "./esm/Table/Table.jsTable/Table.js",
  "TableBody": "./esm/TableBody/TableBody.js",
  "TableCell": "./esm/TableCell/TableCell.js",
  "TableContainer": "./esm/TableContainer/TableContainer.js",
  "TableFooter": "./esm/TableFooter/TableFooter.js",
  "TableHead": "./esm/TableHead/TableHead.js",
  "TablePagination": "./esm/TablePagination/TablePagination.js",
  "TableRow": "./esm/TableRow/TableRow.js",
  "TableSortLabel": "./esm/TableSortLabel/TableSortLabel.js",
  "Tabs": "./esm/Tabs/Tabs.js",
  "TextField": "./esm/TextField/TextField.js",
  "TextareaAutosize": "./esm/TextareaAutosize/TextareaAutosize.js",
  "Toolbar": "./esm/Toolbar/Toolbar.js",
  "Tooltip": "./esm/Tooltip/Tooltip.js",
  "Typography": "./esm/Typography/Typography.js",
  "Unstable_TrapFocus": "./esm/Unstable_TrapFocus/Unstable_TrapFocus.js",
  "Zoom": "./esm/Zoom/Zoom.js",
}
